LICENSE.txt
MANIFEST.in
README.md
setup.py
mvShapiroTest/__init__.py
mvShapiroTest/graphs.py
mvShapiroTest/test.py
mvShapiroTest.egg-info/PKG-INFO
mvShapiroTest.egg-info/SOURCES.txt
mvShapiroTest.egg-info/dependency_links.txt
mvShapiroTest.egg-info/top_level.txt