Metadata-Version: 2.1
Name: mvShapiroTest
Version: 0.0.2
Summary: Shapiro-Wilk Test for Multivariate Normality and Skew-Normality
Home-page: https://github.com/CastleMon/mvShapiroTest.git
Author: Blanca Monroy-Castillo, Elizabeth González-Estrada
Author-email: blancamonroy.96@gmail.com, egonzalez@colpos.mx
License: GPLv3
Platform: UNKNOWN
Classifier: Programming Language :: Python :: 3
Classifier: License :: OSI Approved :: MIT License
Classifier: Operating System :: OS Independent
License-File: LICENSE.txt
